hotspot_socks_proxy-3.4.0.dist-info/METADATA
hotspot_socks_proxy-3.4.0.dist-info/WHEEL
hotspot_socks_proxy-3.4.0.dist-info/entry_points.txt
hotspot_socks_proxy-3.4.0.dist-info/licenses/LICENSE
hotspot_socks_proxy/.DS_Store
hotspot_socks_proxy/__init__.py
hotspot_socks_proxy/cmd/__init__.py
hotspot_socks_proxy/cmd/cli.py
hotspot_socks_proxy/cmd/find_wifi.py
hotspot_socks_proxy/cmd/http.py
hotspot_socks_proxy/cmd/socks.py
hotspot_socks_proxy/core/__init__.py
hotspot_socks_proxy/core/network.py
hotspot_socks_proxy/core/proxy.py
hotspot_socks_proxy-3.4.0.dist-info/RECORD
