Metadata-Version: 2.1
Name: hotspot-socks-proxy
Version: 3.4.0
Summary: SOCKS proxy for routing traffic through WiFi interface
Author-Email: tadeasf <business@tadeasfort.com>
Requires-Python: >=3.9
Requires-Dist: typer>=0.15.1
Requires-Dist: prompt-toolkit>=3.0.50
Requires-Dist: rich>=13.9.4
Requires-Dist: psutil>=5.9.0
Requires-Dist: pyperclip>=1.9.0
Requires-Dist: tomli>=2.2.1
Requires-Dist: dnspython>=2.7.0
Requires-Dist: mkdocs-gen-files>=0.5.0
Requires-Dist: loguru>=0.7.3
Requires-Dist: click>=8.1.8
